hexasphere/__init__.py
hexasphere/geometry.py
hexasphere/hexgrid.py
hexasphere/projection.py
hexasphere-0.0.4.dist-info/METADATA
hexasphere-0.0.4.dist-info/WHEEL
hexasphere-0.0.4.dist-info/licenses/LICENSE
hexasphere-0.0.4.dist-info/RECORD
