Metadata-Version: 2.1
Name: hexasphere
Version: 0.0.4
Summary: A module to create (almost) hexagonal grids on a sphere
Project-URL: Homepage, https://github.com/AllphinsPilot/hexasphere
Project-URL: Bug Tracker, https://github.com/AllphinsPilot/hexasphere/issues
Author-email: Marius Alonso <marius@allphins.com>
License: MIT License
Classifier: License :: OSI Approved :: MIT License
Classifier: Operating System :: OS Independent
Classifier: Programming Language :: Python :: 3
Requires-Python: >=3.7
